{
  "group_id": "260617-444-zero-success-02",
  "state": "open",
  "tags": [
    "triage:needs_review"
  ],
  "title": "444 zero-success",
  "summary": "GrowthLoop 4 GrowthLoop (GrowthLoop) - Audience 38540: 0 successfull_exports from pizza tracker found 10 minutes after new export",
  "deterministic_key": "v3|incident:Q3F9LDXG6UJ2NC|org:444|class:zero-success",
  "grouping_version": 3,
  "created_at": "2026-06-22T18:54:54.145Z",
  "updated_at": "2026-06-22T21:34:00.858Z",
  "alert_refs": [
    {
      "incident_id": "Q3F9LDXG6UJ2NC",
      "alert_id": "Q2A8L9ESVAZ9JE"
    }
  ],
  "incident_ids": [
    "Q3F9LDXG6UJ2NC"
  ],
  "related_group_ids": []
}
