{
  "check_id": "chk_q2qpiocascvfh7_q0sjvysm487cfq",
  "source": "pagerduty",
  "incident_id": "Q2QPIOCASCVFH7",
  "alert_id": "Q0SJVYSM487CFQ",
  "state": "blocked",
  "scope": {
    "env": "albertsons",
    "org_id": "6",
    "audience_id": "12609",
    "match_strategy": "any_export_after_alert",
    "alert_created_at": "2026-06-22T04:50:38-07:00",
    "checked_export_run_ids": [],
    "glcli": "glcli --env albertsons bifrost pizza --audience-id 12609 --org-id 6"
  },
  "scope_key": "albertsons|6|12609|unknown_destination|unknown_endpoint|unknown_run",
  "run_evaluations": [],
  "blockers": [
    "missing_export_after_alert"
  ],
  "evidence_artifacts": [],
  "created_at": "2026-06-22T19:01:23.313Z",
  "updated_at": "2026-06-22T19:56:54.362Z"
}
