{
  "annotation": {
    "ts": "2026-06-22T18:59:50.898Z",
    "alert_ref": {
      "incident_id": "Q1IKQF303EXNLG",
      "alert_id": "Q219UFD3K9N1RK"
    },
    "tags": [],
    "decision": "skip",
    "confidence": "high",
    "summary": "Alert is outside the Albertsons sent-to-client slice since 2026-06-18.",
    "source": {
      "kind": "tagger",
      "run_id": "tagrun_20260622185949_260622_albertsons_client_sent_since_260618",
      "script_sha256": "1172a928dda32895163c85b485704e070ad1e9de8ff98687d9bfe8afee1edbde",
      "script_path": "cases/assets/taggers/tagrun_20260622185949_260622_albertsons_client_sent_since_260618/260622-albertsons-client-sent-since-260618.ts"
    }
  },
  "process": {
    "stdout": "{\"decision\":\"skip\",\"confidence\":\"high\",\"summary\":\"Alert is outside the Albertsons sent-to-client slice since 2026-06-18.\"}\n",
    "stderr": "",
    "exit_code": 0
  }
}
