{
  "check_id": "chk_q12a5qfim3f9ln_q3gvov55z30y4r",
  "source": "pagerduty",
  "incident_id": "Q12A5QFIM3F9LN",
  "alert_id": "Q3GVOV55Z30Y4R",
  "state": "healthy_closed",
  "scope": {
    "env": "prod",
    "org_id": "336",
    "audience_id": "35783",
    "match_strategy": "any_export_after_alert",
    "alert_created_at": "2026-05-13T17:18:48-07:00",
    "checked_export_run_ids": [],
    "glcli": "glcli --env prod bifrost pizza --audience-id 35783 --org-id 336"
  },
  "scope_key": "prod|336|35783|unknown_destination|unknown_endpoint|unknown_run",
  "run_evaluations": [
    {
      "export_run_id": "35783-adobe_experience_platform_21768-scheduled__2026-05-15T00:00:00+00:00",
      "health": "healthy",
      "match_basis": "any_export_after_alert",
      "blockers": [],
      "selected_row": {
        "export_run_id": "35783-adobe_experience_platform_21768-scheduled__2026-05-15T00:00:00+00:00",
        "audience_id": "35783",
        "destination_type": "adobe_experience_platform",
        "created_at": "2026-05-15T00:17:04.946473+00:00",
        "snapshotting_state": "snapshotting_finished_no_deltas",
        "export_state": "no_batches",
        "failed_export_count": 0,
        "raw": {
          "export_state": "no_batches",
          "successful_add_count": 0,
          "successful_remove_count": 0,
          "failed_export_count": 0,
          "rejected_row_count": 0,
          "total_row_count": 0,
          "successful_expanded_add_count": 0,
          "successful_expanded_remove_count": 0,
          "failed_expanded_export_count": 0,
          "rejected_expanded_row_count": 0,
          "total_expanded_row_count": 0,
          "enhanced_match_count": 0,
          "enhanced_row_count": 0,
          "enhanced_total_records": 0,
          "total_batch_count": 0,
          "completed_batch_count": 0,
          "successful_batch_count": 0,
          "failed_batch_count": 0,
          "failure_reason": null,
          "info": {
            "internal_audience_id": "35783",
            "export_run_id": "35783-adobe_experience_platform_21768-scheduled__2026-05-15T00:00:00+00:00",
            "export_timestamp": "2026-05-15 00:17:04",
            "created_at": "2026-05-15T00:17:04.946473+00:00"
          },
          "snapshotting_state": "snapshotting_finished_no_deltas"
        }
      }
    }
  ],
  "blockers": [],
  "evidence_artifacts": [],
  "created_at": "2026-05-16T20:46:07.288Z",
  "updated_at": "2026-05-16T23:48:59.164Z",
  "closed_at": "2026-05-16T23:48:59.164Z"
}
