{
  "check_id": "chk_q2t09vcln9mrz8_q0iokgy9ur4xdo",
  "source": "pagerduty",
  "incident_id": "Q2T09VCLN9MRZ8",
  "alert_id": "Q0IOKGY9UR4XDO",
  "state": "blocked",
  "scope": {
    "env": "albertsons",
    "org_id": "6",
    "audience_id": "8521",
    "endpoint_id": "app_liveramp_activation_26",
    "destination_type": "live_ramp_activation",
    "checked_export_run_ids": [
      "8521-live_ramp_activation_1698-scheduled__2026-05-06T00:00:00+00:00",
      "8521-live_ramp_activation_1698-manual__2026-05-06T18:09:59+00:00"
    ],
    "glcli": "glcli --env albertsons bifrost pizza --audience-id 8521 --org-id 6"
  },
  "scope_key": "albertsons|6|8521|live_ramp_activation|app_liveramp_activation_26|8521-live_ramp_activation_1698-scheduled__2026-05-06T00:00:00+00:00,8521-live_ramp_activation_1698-manual__2026-05-06T18:09:59+00:00",
  "run_evaluations": [
    {
      "export_run_id": "8521-live_ramp_activation_1698-scheduled__2026-05-06T00:00:00+00:00",
      "health": "blocked",
      "match_basis": "checked_export_run_id",
      "blockers": [
        "failed_export_count",
        "export_error"
      ],
      "selected_row": {
        "export_run_id": "8521-live_ramp_activation_1698-scheduled__2026-05-06T00:00:00+00:00",
        "audience_id": "8521",
        "endpoint_id": "app_liveramp_activation_26",
        "destination_type": "live_ramp_activation",
        "created_at": "2026-05-06T02:25:38.313457+00:00",
        "snapshotting_state": "snapshotting_finished",
        "export_state": "export_error",
        "failed_export_count": 359189,
        "raw": {
          "export_state": "export_error",
          "successful_add_count": 0,
          "successful_remove_count": 0,
          "failed_export_count": 359189,
          "rejected_row_count": 370345,
          "total_row_count": 729534,
          "successful_expanded_add_count": 0,
          "successful_expanded_remove_count": 0,
          "failed_expanded_export_count": 359189,
          "rejected_expanded_row_count": 370345,
          "total_expanded_row_count": 729534,
          "enhanced_match_count": 0,
          "enhanced_row_count": 0,
          "enhanced_total_records": 0,
          "total_batch_count": 1,
          "completed_batch_count": 1,
          "successful_batch_count": 0,
          "failed_batch_count": 1,
          "failure_reason": null,
          "info": {
            "internal_export_id": "8521-live_ramp_activation_1698-scheduled__2026-05-06T00:00:00+00:00-20260506022359",
            "export_run_id": "8521-live_ramp_activation_1698-scheduled__2026-05-06T00:00:00+00:00",
            "audience_id": null,
            "internal_audience_id": "8521",
            "audience_name": "A_LR_RMN_FY23ExpPcg_PastaDishes_L26W",
            "organization_id": "6",
            "organization_name": "albertsons",
            "platform": "live_ramp_activation",
            "endpoint_id": "app_liveramp_activation_26",
            "export_timestamp": "2026-05-06 02:23:59",
            "error_file_uri": "gs://emgi-outbound-prod-bkt-01/batch_errors/104b4e2d-a87b-4fda-a584-da5b2da7ccd4.csv",
            "created_at": "2026-05-06T02:25:38.313457+00:00",
            "export_complete_response": null
          },
          "snapshotting_state": "snapshotting_finished"
        }
      }
    },
    {
      "export_run_id": "8521-live_ramp_activation_1698-manual__2026-05-06T18:09:59+00:00",
      "health": "healthy",
      "match_basis": "checked_export_run_id",
      "blockers": [],
      "selected_row": {
        "export_run_id": "8521-live_ramp_activation_1698-manual__2026-05-06T18:09:59+00:00",
        "audience_id": "8521",
        "endpoint_id": "app_liveramp_activation_26",
        "destination_type": "live_ramp_activation",
        "created_at": "2026-05-06T21:03:48.432380+00:00",
        "snapshotting_state": "snapshotting_finished",
        "export_state": "export_finished",
        "failed_export_count": 0,
        "raw": {
          "export_state": "export_finished",
          "successful_add_count": 5,
          "successful_remove_count": 0,
          "failed_export_count": 0,
          "rejected_row_count": 70,
          "total_row_count": 75,
          "successful_expanded_add_count": 0,
          "successful_expanded_remove_count": 0,
          "failed_expanded_export_count": 0,
          "rejected_expanded_row_count": 70,
          "total_expanded_row_count": 75,
          "enhanced_match_count": 0,
          "enhanced_row_count": 0,
          "enhanced_total_records": 0,
          "total_batch_count": 1,
          "completed_batch_count": 1,
          "successful_batch_count": 1,
          "failed_batch_count": 0,
          "failure_reason": null,
          "info": {
            "internal_export_id": "8521-live_ramp_activation_1698-manual__2026-05-06T18:09:59+00:00-20260506210214",
            "export_run_id": "8521-live_ramp_activation_1698-manual__2026-05-06T18:09:59+00:00",
            "audience_id": null,
            "internal_audience_id": "8521",
            "audience_name": "A_LR_RMN_FY23ExpPcg_PastaDishes_L26W",
            "organization_id": "6",
            "organization_name": "albertsons",
            "platform": "live_ramp_activation",
            "endpoint_id": "app_liveramp_activation_26",
            "export_timestamp": "2026-05-06 21:02:14",
            "error_file_uri": "gs://emgi-outbound-prod-bkt-01/batch_errors/128872f3-66c3-4154-b114-c7c0aa89e59d.csv",
            "created_at": "2026-05-06T21:03:48.432380+00:00",
            "export_complete_response": null
          },
          "snapshotting_state": "snapshotting_finished"
        }
      }
    }
  ],
  "blockers": [
    "failed_export_count",
    "export_error"
  ],
  "evidence_artifacts": [],
  "created_at": "2026-05-16T01:35:43.498Z",
  "updated_at": "2026-05-16T01:35:43.498Z"
}
